{
  "ComponentAllowCustomization": true,
  "ComponentChangedSinceFileImport": true,
  "ComponentDefinitionInfo": {
    "AllowAccessToGlobals": false,
    "Children": [
      {
        "AllowAccessToGlobals": true,
        "Children": [],
        "ControlPropertyState": [
          {
            "AFDDataSourceName": "",
            "AutoRuleBindingEnabled": false,
            "AutoRuleBindingString": "RGBA(56, 96, 178, 1)",
            "InvariantPropertyName": "Fill",
            "IsLockable": false,
            "NameMapSourceSchema": "?"
          },
          "DisabledFill",
          "PressedFill",
          "HoverFill",
          "BorderColor",
          "BorderStyle",
          "FocusedBorderColor",
          "DisplayMode",
          "X",
          "Y",
          "Width",
          "Height",
          "ZIndex",
          "BorderThickness",
          "FocusedBorderThickness"
        ],
        "ControlUniqueId": "37",
        "HasDynamicProperties": false,
        "Index": 0,
        "IsAutoGenerated": false,
        "IsDataControl": false,
        "IsFromScreenLayout": false,
        "IsGroupControl": false,
        "IsLocked": false,
        "LayoutName": "",
        "MetaDataIDKey": "",
        "Name": "Rectangle1",
        "Parent": "ModalConfirmation",
        "PersistMetaDataIDKey": false,
        "PublishOrderIndex": 1051,
        "Rules": [
          {
            "Category": "Design",
            "InvariantScript": "Color.White",
            "Property": "Fill",
            "RuleProviderType": "Unknown"
          },
          {
            "Category": "Design",
            "InvariantScript": "Self.Fill",
            "Property": "DisabledFill",
            "RuleProviderType": "Unknown"
          },
          {
            "Category": "Design",
            "InvariantScript": "Self.Fill",
            "Property": "PressedFill",
            "RuleProviderType": "Unknown"
          },
          {
            "Category": "Design",
            "InvariantScript": "Self.Fill",
            "Property": "HoverFill",
            "RuleProviderType": "Unknown"
          },
          {
            "Category": "Design",
            "InvariantScript": "RGBA(0, 18, 107, 1)",
            "Property": "BorderColor",
            "RuleProviderType": "Unknown"
          },
          {
            "Category": "Design",
            "InvariantScript": "BorderStyle.Solid",
            "Property": "BorderStyle",
            "RuleProviderType": "Unknown"
          },
          {
            "Category": "Design",
            "InvariantScript": "Self.BorderColor",
            "Property": "FocusedBorderColor",
            "RuleProviderType": "Unknown"
          },
          {
            "Category": "Design",
            "InvariantScript": "DisplayMode.Edit",
            "Property": "DisplayMode",
            "RuleProviderType": "Unknown"
          },
          {
            "Category": "Design",
            "InvariantScript": "455",
            "Property": "X",
            "RuleProviderType": "Unknown"
          },
          {
            "Category": "Design",
            "InvariantScript": "255",
            "Property": "Y",
            "RuleProviderType": "Unknown"
          },
          {
            "Category": "Design",
            "InvariantScript": "456",
            "Property": "Width",
            "RuleProviderType": "Unknown"
          },
          {
            "Category": "Design",
            "InvariantScript": "259",
            "Property": "Height",
            "RuleProviderType": "Unknown"
          },
          {
            "Category": "Design",
            "InvariantScript": "1",
            "Property": "ZIndex",
            "RuleProviderType": "Unknown"
          },
          {
            "Category": "Design",
            "InvariantScript": "0",
            "Property": "BorderThickness",
            "RuleProviderType": "Unknown"
          },
          {
            "Category": "Design",
            "InvariantScript": "2",
            "Property": "FocusedBorderThickness",
            "RuleProviderType": "Unknown"
          }
        ],
        "StyleName": "defaultRectangleStyle",
        "Template": {
          "CustomGroupControlTemplateName": "",
          "FirstParty": true,
          "Id": "http://microsoft.com/appmagic/shapes/rectangle",
          "IsComponentDefinition": false,
          "IsCustomGroupControlTemplate": false,
          "IsPremiumPcfControl": false,
          "LastModifiedTimestamp": "0",
          "Name": "rectangle",
          "OverridableProperties": {},
          "Version": "2.3.0"
        },
        "Type": "ControlInfo",
        "VariantName": ""
      },
      {
        "AllowAccessToGlobals": true,
        "Children": [],
        "ControlPropertyState": [
          {
            "AFDDataSourceName": "",
            "AutoRuleBindingEnabled": false,
            "AutoRuleBindingString": "Icon.Printing3D",
            "InvariantPropertyName": "Icon",
            "IsLockable": false,
            "NameMapSourceSchema": "?"
          },
          {
            "AFDDataSourceName": "",
            "AutoRuleBindingEnabled": false,
            "AutoRuleBindingString": "RGBA(0, 18, 107, 1)",
            "InvariantPropertyName": "Color",
            "IsLockable": false,
            "NameMapSourceSchema": "?"
          },
          "DisabledColor",
          "PressedColor",
          "HoverColor",
          "Fill",
          "DisabledFill",
          "PressedFill",
          "HoverFill",
          "DisplayMode",
          "X",
          "Y",
          "Width",
          "Height",
          "BorderStyle",
          "BorderColor",
          "DisabledBorderColor",
          "PressedBorderColor",
          "HoverBorderColor",
          "FocusedBorderColor",
          "ZIndex",
          "BorderThickness",
          "FocusedBorderThickness"
        ],
        "ControlUniqueId": "38",
        "HasDynamicProperties": false,
        "Index": 0,
        "IsAutoGenerated": false,
        "IsDataControl": false,
        "IsFromScreenLayout": false,
        "IsGroupControl": false,
        "IsLocked": false,
        "LayoutName": "",
        "MetaDataIDKey": "",
        "Name": "Icon4",
        "Parent": "ModalConfirmation",
        "PersistMetaDataIDKey": false,
        "PublishOrderIndex": 1052,
        "Rules": [
          {
            "Category": "Design",
            "InvariantScript": "ModalConfirmation.ModalIcon",
            "Property": "Icon",
            "RuleProviderType": "Unknown"
          },
          {
            "Category": "Design",
            "InvariantScript": "ModalConfirmation.ModalIconColor",
            "Property": "Color",
            "RuleProviderType": "Unknown"
          },
          {
            "Category": "Design",
            "InvariantScript": "RGBA(244, 244, 244, 1)",
            "Property": "DisabledColor",
            "RuleProviderType": "Unknown"
          },
          {
            "Category": "Design",
            "InvariantScript": "ColorFade(Self.Color, -20%)",
            "Property": "PressedColor",
            "RuleProviderType": "Unknown"
          },
          {
            "Category": "Design",
            "InvariantScript": "ColorFade(Self.Color, 20%)",
            "Property": "HoverColor",
            "RuleProviderType": "Unknown"
          },
          {
            "Category": "Design",
            "InvariantScript": "RGBA(0, 0, 0, 0)",
            "Property": "Fill",
            "RuleProviderType": "Unknown"
          },
          {
            "Category": "Design",
            "InvariantScript": "Self.Fill",
            "Property": "DisabledFill",
            "RuleProviderType": "Unknown"
          },
          {
            "Category": "Design",
            "InvariantScript": "Self.Fill",
            "Property": "PressedFill",
            "RuleProviderType": "Unknown"
          },
          {
            "Category": "Design",
            "InvariantScript": "Self.Fill",
            "Property": "HoverFill",
            "RuleProviderType": "Unknown"
          },
          {
            "Category": "Design",
            "InvariantScript": "DisplayMode.Edit",
            "Property": "DisplayMode",
            "RuleProviderType": "Unknown"
          },
          {
            "Category": "Design",
            "InvariantScript": "651",
            "Property": "X",
            "RuleProviderType": "Unknown"
          },
          {
            "Category": "Design",
            "InvariantScript": "271",
            "Property": "Y",
            "RuleProviderType": "Unknown"
          },
          {
            "Category": "Design",
            "InvariantScript": "64",
            "Property": "Width",
            "RuleProviderType": "Unknown"
          },
          {
            "Category": "Design",
            "InvariantScript": "64",
            "Property": "Height",
            "RuleProviderType": "Unknown"
          },
          {
            "Category": "Design",
            "InvariantScript": "BorderStyle.Solid",
            "Property": "BorderStyle",
            "RuleProviderType": "Unknown"
          },
          {
            "Category": "Design",
            "InvariantScript": "RGBA(0, 18, 107, 1)",
            "Property": "BorderColor",
            "RuleProviderType": "Unknown"
          },
          {
            "Category": "Design",
            "InvariantScript": "RGBA(166, 166, 166, 1)",
            "Property": "DisabledBorderColor",
            "RuleProviderType": "Unknown"
          },
          {
            "Category": "Design",
            "InvariantScript": "ColorFade(Self.BorderColor, -20%)",
            "Property": "PressedBorderColor",
            "RuleProviderType": "Unknown"
          },
          {
            "Category": "Design",
            "InvariantScript": "ColorFade(Self.BorderColor, 20%)",
            "Property": "HoverBorderColor",
            "RuleProviderType": "Unknown"
          },
          {
            "Category": "Design",
            "InvariantScript": "Self.BorderColor",
            "Property": "FocusedBorderColor",
            "RuleProviderType": "Unknown"
          },
          {
            "Category": "Design",
            "InvariantScript": "3",
            "Property": "ZIndex",
            "RuleProviderType": "Unknown"
          },
          {
            "Category": "Design",
            "InvariantScript": "0",
            "Property": "BorderThickness",
            "RuleProviderType": "Unknown"
          },
          {
            "Category": "Design",
            "InvariantScript": "2",
            "Property": "FocusedBorderThickness",
            "RuleProviderType": "Unknown"
          }
        ],
        "StyleName": "defaultIconStyle",
        "Template": {
          "CustomGroupControlTemplateName": "",
          "FirstParty": true,
          "Id": "http://microsoft.com/appmagic/icon",
          "IsComponentDefinition": false,
          "IsCustomGroupControlTemplate": false,
          "IsPremiumPcfControl": false,
          "LastModifiedTimestamp": "0",
          "Name": "icon",
          "OverridableProperties": {},
          "Version": "2.5.0"
        },
        "Type": "ControlInfo",
        "VariantName": "3DPrinting"
      },
      {
        "AllowAccessToGlobals": true,
        "Children": [],
        "ControlPropertyState": [
          "Live",
          "Overflow",
          {
            "AFDDataSourceName": "",
            "AutoRuleBindingEnabled": false,
            "AutoRuleBindingString": "\"Text\"",
            "InvariantPropertyName": "Text",
            "IsLockable": false,
            "NameMapSourceSchema": "?"
          },
          "Role",
          "Color",
          "DisabledColor",
          "PressedColor",
          "HoverColor",
          "BorderColor",
          "DisabledBorderColor",
          "PressedBorderColor",
          "HoverBorderColor",
          "BorderStyle",
          "FocusedBorderColor",
          "Fill",
          "DisabledFill",
          "PressedFill",
          "HoverFill",
          "Font",
          "FontWeight",
          {
            "AFDDataSourceName": "",
            "AutoRuleBindingEnabled": false,
            "AutoRuleBindingString": "",
            "InvariantPropertyName": "Align",
            "IsLockable": false,
            "NameMapSourceSchema": "?"
          },
          "VerticalAlign",
          "X",
          "Y",
          "Width",
          "Height",
          "DisplayMode",
          "ZIndex",
          "LineHeight",
          "BorderThickness",
          "FocusedBorderThickness",
          "Size",
          "Italic",
          "Underline",
          "Strikethrough",
          "PaddingTop",
          "PaddingRight",
          "PaddingBottom",
          "PaddingLeft"
        ],
        "ControlUniqueId": "39",
        "HasDynamicProperties": false,
        "Index": 0,
        "IsAutoGenerated": false,
        "IsDataControl": false,
        "IsFromScreenLayout": false,
        "IsGroupControl": false,
        "IsLocked": false,
        "LayoutName": "",
        "MetaDataIDKey": "",
        "Name": "Label4",
        "Parent": "ModalConfirmation",
        "PersistMetaDataIDKey": false,
        "PublishOrderIndex": 1053,
        "Rules": [
          {
            "Category": "Data",
            "InvariantScript": "Live.Off",
            "Property": "Live",
            "RuleProviderType": "Unknown"
          },
          {
            "Category": "Data",
            "InvariantScript": "ModalConfirmation.ModalText",
            "Property": "Text",
            "RuleProviderType": "Unknown"
          },
          {
            "Category": "Data",
            "InvariantScript": "TextRole.Default",
            "Property": "Role",
            "RuleProviderType": "Unknown"
          },
          {
            "Category": "Design",
            "InvariantScript": "Overflow.Hidden",
            "Property": "Overflow",
            "RuleProviderType": "Unknown"
          },
          {
            "Category": "Design",
            "InvariantScript": "RGBA(0, 0, 0, 1)",
            "Property": "Color",
            "RuleProviderType": "Unknown"
          },
          {
            "Category": "Design",
            "InvariantScript": "RGBA(166, 166, 166, 1)",
            "Property": "DisabledColor",
            "RuleProviderType": "Unknown"
          },
          {
            "Category": "Design",
            "InvariantScript": "Self.Color",
            "Property": "PressedColor",
            "RuleProviderType": "Unknown"
          },
          {
            "Category": "Design",
            "InvariantScript": "Self.Color",
            "Property": "HoverColor",
            "RuleProviderType": "Unknown"
          },
          {
            "Category": "Design",
            "InvariantScript": "RGBA(0, 18, 107, 1)",
            "Property": "BorderColor",
            "RuleProviderType": "Unknown"
          },
          {
            "Category": "Design",
            "InvariantScript": "RGBA(56, 56, 56, 1)",
            "Property": "DisabledBorderColor",
            "RuleProviderType": "Unknown"
          },
          {
            "Category": "Design",
            "InvariantScript": "Self.BorderColor",
            "Property": "PressedBorderColor",
            "RuleProviderType": "Unknown"
          },
          {
            "Category": "Design",
            "InvariantScript": "Self.BorderColor",
            "Property": "HoverBorderColor",
            "RuleProviderType": "Unknown"
          },
          {
            "Category": "Design",
            "InvariantScript": "BorderStyle.Solid",
            "Property": "BorderStyle",
            "RuleProviderType": "Unknown"
          },
          {
            "Category": "Design",
            "InvariantScript": "Self.BorderColor",
            "Property": "FocusedBorderColor",
            "RuleProviderType": "Unknown"
          },
          {
            "Category": "Design",
            "InvariantScript": "RGBA(0, 0, 0, 0)",
            "Property": "Fill",
            "RuleProviderType": "Unknown"
          },
          {
            "Category": "Design",
            "InvariantScript": "RGBA(0, 0, 0, 0)",
            "Property": "DisabledFill",
            "RuleProviderType": "Unknown"
          },
          {
            "Category": "Design",
            "InvariantScript": "Self.Fill",
            "Property": "PressedFill",
            "RuleProviderType": "Unknown"
          },
          {
            "Category": "Design",
            "InvariantScript": "Self.Fill",
            "Property": "HoverFill",
            "RuleProviderType": "Unknown"
          },
          {
            "Category": "Design",
            "InvariantScript": "Font.'Open Sans'",
            "Property": "Font",
            "RuleProviderType": "Unknown"
          },
          {
            "Category": "Design",
            "InvariantScript": "FontWeight.Normal",
            "Property": "FontWeight",
            "RuleProviderType": "Unknown"
          },
          {
            "Category": "Design",
            "InvariantScript": "Align.Center",
            "Property": "Align",
            "RuleProviderType": "Unknown"
          },
          {
            "Category": "Design",
            "InvariantScript": "VerticalAlign.Middle",
            "Property": "VerticalAlign",
            "RuleProviderType": "Unknown"
          },
          {
            "Category": "Design",
            "InvariantScript": "496",
            "Property": "X",
            "RuleProviderType": "Unknown"
          },
          {
            "Category": "Design",
            "InvariantScript": "341",
            "Property": "Y",
            "RuleProviderType": "Unknown"
          },
          {
            "Category": "Design",
            "InvariantScript": "374",
            "Property": "Width",
            "RuleProviderType": "Unknown"
          },
          {
            "Category": "Design",
            "InvariantScript": "99",
            "Property": "Height",
            "RuleProviderType": "Unknown"
          },
          {
            "Category": "Design",
            "InvariantScript": "DisplayMode.Edit",
            "Property": "DisplayMode",
            "RuleProviderType": "Unknown"
          },
          {
            "Category": "Design",
            "InvariantScript": "2",
            "Property": "ZIndex",
            "RuleProviderType": "Unknown"
          },
          {
            "Category": "Design",
            "InvariantScript": "1.2",
            "Property": "LineHeight",
            "RuleProviderType": "Unknown"
          },
          {
            "Category": "Design",
            "InvariantScript": "0",
            "Property": "BorderThickness",
            "RuleProviderType": "Unknown"
          },
          {
            "Category": "Design",
            "InvariantScript": "0",
            "Property": "FocusedBorderThickness",
            "RuleProviderType": "Unknown"
          },
          {
            "Category": "Design",
            "InvariantScript": "13",
            "Property": "Size",
            "RuleProviderType": "Unknown"
          },
          {
            "Category": "Design",
            "InvariantScript": "false",
            "Property": "Italic",
            "RuleProviderType": "Unknown"
          },
          {
            "Category": "Design",
            "InvariantScript": "false",
            "Property": "Underline",
            "RuleProviderType": "Unknown"
          },
          {
            "Category": "Design",
            "InvariantScript": "false",
            "Property": "Strikethrough",
            "RuleProviderType": "Unknown"
          },
          {
            "Category": "Design",
            "InvariantScript": "5",
            "Property": "PaddingTop",
            "RuleProviderType": "Unknown"
          },
          {
            "Category": "Design",
            "InvariantScript": "5",
            "Property": "PaddingRight",
            "RuleProviderType": "Unknown"
          },
          {
            "Category": "Design",
            "InvariantScript": "5",
            "Property": "PaddingBottom",
            "RuleProviderType": "Unknown"
          },
          {
            "Category": "Design",
            "InvariantScript": "5",
            "Property": "PaddingLeft",
            "RuleProviderType": "Unknown"
          }
        ],
        "StyleName": "defaultLabelStyle",
        "Template": {
          "CustomGroupControlTemplateName": "",
          "FirstParty": true,
          "Id": "http://microsoft.com/appmagic/label",
          "IsComponentDefinition": false,
          "IsCustomGroupControlTemplate": false,
          "IsPremiumPcfControl": false,
          "LastModifiedTimestamp": "0",
          "Name": "label",
          "OverridableProperties": {},
          "Version": "2.5.1"
        },
        "Type": "ControlInfo",
        "VariantName": ""
      },
      {
        "AllowAccessToGlobals": true,
        "Children": [],
        "ControlPropertyState": [
          {
            "AFDDataSourceName": "",
            "AutoRuleBindingEnabled": false,
            "AutoRuleBindingString": "\"Button\"",
            "InvariantPropertyName": "Text",
            "IsLockable": false,
            "NameMapSourceSchema": "?"
          },
          "BorderColor",
          "DisabledBorderColor",
          "PressedBorderColor",
          "HoverBorderColor",
          "BorderStyle",
          "FocusedBorderColor",
          {
            "AFDDataSourceName": "",
            "AutoRuleBindingEnabled": false,
            "AutoRuleBindingString": "RGBA(255, 255, 255, 1)",
            "InvariantPropertyName": "Color",
            "IsLockable": false,
            "NameMapSourceSchema": "?"
          },
          "DisabledColor",
          "PressedColor",
          {
            "AFDDataSourceName": "",
            "AutoRuleBindingEnabled": false,
            "AutoRuleBindingString": "RGBA(255, 255, 255, 1)",
            "InvariantPropertyName": "HoverColor",
            "IsLockable": false,
            "NameMapSourceSchema": "?"
          },
          "DisplayMode",
          {
            "AFDDataSourceName": "",
            "AutoRuleBindingEnabled": false,
            "AutoRuleBindingString": "RGBA(56, 96, 178, 1)",
            "InvariantPropertyName": "Fill",
            "IsLockable": false,
            "NameMapSourceSchema": "?"
          },
          "DisabledFill",
          "PressedFill",
          {
            "AFDDataSourceName": "",
            "AutoRuleBindingEnabled": false,
            "AutoRuleBindingString": "ColorFade(RGBA(56, 96, 178, 1), -20%)",
            "InvariantPropertyName": "HoverFill",
            "IsLockable": false,
            "NameMapSourceSchema": "?"
          },
          "Font",
          {
            "AFDDataSourceName": "",
            "AutoRuleBindingEnabled": false,
            "AutoRuleBindingString": "",
            "InvariantPropertyName": "FontWeight",
            "IsLockable": false,
            "NameMapSourceSchema": "?"
          },
          {
            "AFDDataSourceName": "",
            "AutoRuleBindingEnabled": false,
            "AutoRuleBindingString": "",
            "InvariantPropertyName": "Align",
            "IsLockable": false,
            "NameMapSourceSchema": "?"
          },
          "VerticalAlign",
          "X",
          "Y",
          {
            "AFDDataSourceName": "",
            "AutoRuleBindingEnabled": false,
            "AutoRuleBindingString": "160",
            "InvariantPropertyName": "Width",
            "IsLockable": false,
            "NameMapSourceSchema": "?"
          },
          "Height",
          "ZIndex",
          {
            "AFDDataSourceName": "",
            "AutoRuleBindingEnabled": false,
            "AutoRuleBindingString": "",
            "InvariantPropertyName": "RadiusTopLeft",
            "IsLockable": false,
            "NameMapSourceSchema": "?"
          },
          {
            "AFDDataSourceName": "",
            "AutoRuleBindingEnabled": false,
            "AutoRuleBindingString": "",
            "InvariantPropertyName": "RadiusTopRight",
            "IsLockable": false,
            "NameMapSourceSchema": "?"
          },
          {
            "AFDDataSourceName": "",
            "AutoRuleBindingEnabled": false,
            "AutoRuleBindingString": "",
            "InvariantPropertyName": "RadiusBottomLeft",
            "IsLockable": false,
            "NameMapSourceSchema": "?"
          },
          {
            "AFDDataSourceName": "",
            "AutoRuleBindingEnabled": false,
            "AutoRuleBindingString": "",
            "InvariantPropertyName": "RadiusBottomRight",
            "IsLockable": false,
            "NameMapSourceSchema": "?"
          },
          {
            "AFDDataSourceName": "",
            "AutoRuleBindingEnabled": false,
            "AutoRuleBindingString": "",
            "InvariantPropertyName": "BorderThickness",
            "IsLockable": false,
            "NameMapSourceSchema": "?"
          },
          "FocusedBorderThickness",
          "Size",
          "Italic",
          "Underline",
          "Strikethrough",
          {
            "AFDDataSourceName": "",
            "AutoRuleBindingEnabled": false,
            "AutoRuleBindingString": "",
            "InvariantPropertyName": "PaddingLeft",
            "IsLockable": false,
            "NameMapSourceSchema": "?"
          },
          {
            "AFDDataSourceName": "",
            "AutoRuleBindingEnabled": false,
            "AutoRuleBindingString": "false",
            "InvariantPropertyName": "OnSelect",
            "IsLockable": false,
            "NameMapSourceSchema": "?"
          }
        ],
        "ControlUniqueId": "40",
        "HasDynamicProperties": false,
        "Index": 0,
        "IsAutoGenerated": false,
        "IsDataControl": false,
        "IsFromScreenLayout": false,
        "IsGroupControl": false,
        "IsLocked": false,
        "LayoutName": "",
        "MetaDataIDKey": "",
        "Name": "Button1_2",
        "Parent": "ModalConfirmation",
        "PersistMetaDataIDKey": false,
        "PublishOrderIndex": 1054,
        "Rules": [
          {
            "Category": "Data",
            "InvariantScript": "ModalConfirmation.LeftBtnText",
            "Property": "Text",
            "RuleProviderType": "Unknown"
          },
          {
            "Category": "Design",
            "InvariantScript": "ColorFade(Self.Fill, -15%)",
            "Property": "BorderColor",
            "RuleProviderType": "Unknown"
          },
          {
            "Category": "Design",
            "InvariantScript": "RGBA(166, 166, 166, 1)",
            "Property": "DisabledBorderColor",
            "RuleProviderType": "Unknown"
          },
          {
            "Category": "Design",
            "InvariantScript": "Self.Fill",
            "Property": "PressedBorderColor",
            "RuleProviderType": "Unknown"
          },
          {
            "Category": "Design",
            "InvariantScript": "ColorFade(Self.BorderColor, 20%)",
            "Property": "HoverBorderColor",
            "RuleProviderType": "Unknown"
          },
          {
            "Category": "Design",
            "InvariantScript": "BorderStyle.Solid",
            "Property": "BorderStyle",
            "RuleProviderType": "Unknown"
          },
          {
            "Category": "Design",
            "InvariantScript": "Self.BorderColor",
            "Property": "FocusedBorderColor",
            "RuleProviderType": "Unknown"
          },
          {
            "Category": "Design",
            "InvariantScript": "RGBA(51, 51, 51, 1)",
            "Property": "Color",
            "RuleProviderType": "Unknown"
          },
          {
            "Category": "Design",
            "InvariantScript": "RGBA(166, 166, 166, 1)",
            "Property": "DisabledColor",
            "RuleProviderType": "Unknown"
          },
          {
            "Category": "Design",
            "InvariantScript": "Self.Fill",
            "Property": "PressedColor",
            "RuleProviderType": "Unknown"
          },
          {
            "Category": "Design",
            "InvariantScript": "RGBA(70, 70, 70, 1)",
            "Property": "HoverColor",
            "RuleProviderType": "Unknown"
          },
          {
            "Category": "Design",
            "InvariantScript": "DisplayMode.Edit",
            "Property": "DisplayMode",
            "RuleProviderType": "Unknown"
          },
          {
            "Category": "Design",
            "InvariantScript": "ColorFade(RGBA(70, 70, 70, 1),90%)",
            "Property": "Fill",
            "RuleProviderType": "Unknown"
          },
          {
            "Category": "Design",
            "InvariantScript": "RGBA(244, 244, 244, 1)",
            "Property": "DisabledFill",
            "RuleProviderType": "Unknown"
          },
          {
            "Category": "Design",
            "InvariantScript": "Self.Color",
            "Property": "PressedFill",
            "RuleProviderType": "Unknown"
          },
          {
            "Category": "Design",
            "InvariantScript": "ColorFade(RGBA(70, 70, 70, 1), 85%)",
            "Property": "HoverFill",
            "RuleProviderType": "Unknown"
          },
          {
            "Category": "Design",
            "InvariantScript": "Font.'Open Sans'",
            "Property": "Font",
            "RuleProviderType": "Unknown"
          },
          {
            "Category": "Design",
            "InvariantScript": "FontWeight.Normal",
            "Property": "FontWeight",
            "RuleProviderType": "Unknown"
          },
          {
            "Category": "Design",
            "InvariantScript": "Align.Left",
            "Property": "Align",
            "RuleProviderType": "Unknown"
          },
          {
            "Category": "Design",
            "InvariantScript": "VerticalAlign.Middle",
            "Property": "VerticalAlign",
            "RuleProviderType": "Unknown"
          },
          {
            "Category": "Design",
            "InvariantScript": "486",
            "Property": "X",
            "RuleProviderType": "Unknown"
          },
          {
            "Category": "Design",
            "InvariantScript": "440",
            "Property": "Y",
            "RuleProviderType": "Unknown"
          },
          {
            "Category": "Design",
            "InvariantScript": "165",
            "Property": "Width",
            "RuleProviderType": "Unknown"
          },
          {
            "Category": "Design",
            "InvariantScript": "40",
            "Property": "Height",
            "RuleProviderType": "Unknown"
          },
          {
            "Category": "Design",
            "InvariantScript": "4",
            "Property": "ZIndex",
            "RuleProviderType": "Unknown"
          },
          {
            "Category": "Design",
            "InvariantScript": "5",
            "Property": "RadiusTopLeft",
            "RuleProviderType": "Unknown"
          },
          {
            "Category": "Design",
            "InvariantScript": "5",
            "Property": "RadiusTopRight",
            "RuleProviderType": "Unknown"
          },
          {
            "Category": "Design",
            "InvariantScript": "5",
            "Property": "RadiusBottomLeft",
            "RuleProviderType": "Unknown"
          },
          {
            "Category": "Design",
            "InvariantScript": "5",
            "Property": "RadiusBottomRight",
            "RuleProviderType": "Unknown"
          },
          {
            "Category": "Design",
            "InvariantScript": "0",
            "Property": "BorderThickness",
            "RuleProviderType": "Unknown"
          },
          {
            "Category": "Design",
            "InvariantScript": "4",
            "Property": "FocusedBorderThickness",
            "RuleProviderType": "Unknown"
          },
          {
            "Category": "Design",
            "InvariantScript": "15",
            "Property": "Size",
            "RuleProviderType": "Unknown"
          },
          {
            "Category": "Design",
            "InvariantScript": "false",
            "Property": "Italic",
            "RuleProviderType": "Unknown"
          },
          {
            "Category": "Design",
            "InvariantScript": "false",
            "Property": "Underline",
            "RuleProviderType": "Unknown"
          },
          {
            "Category": "Design",
            "InvariantScript": "false",
            "Property": "Strikethrough",
            "RuleProviderType": "Unknown"
          },
          {
            "Category": "Design",
            "InvariantScript": "50",
            "Property": "PaddingLeft",
            "RuleProviderType": "Unknown"
          },
          {
            "Category": "Behavior",
            "InvariantScript": "",
            "Property": "OnSelect",
            "RuleProviderType": "Unknown"
          }
        ],
        "StyleName": "defaultButtonStyle",
        "Template": {
          "CustomGroupControlTemplateName": "",
          "FirstParty": true,
          "Id": "http://microsoft.com/appmagic/button",
          "IsComponentDefinition": false,
          "IsCustomGroupControlTemplate": false,
          "IsPremiumPcfControl": false,
          "LastModifiedTimestamp": "0",
          "Name": "button",
          "OverridableProperties": {},
          "Version": "2.2.0"
        },
        "Type": "ControlInfo",
        "VariantName": ""
      },
      {
        "AllowAccessToGlobals": true,
        "Children": [],
        "ControlPropertyState": [
          {
            "AFDDataSourceName": "",
            "AutoRuleBindingEnabled": false,
            "AutoRuleBindingString": "\"Button\"",
            "InvariantPropertyName": "Text",
            "IsLockable": false,
            "NameMapSourceSchema": "?"
          },
          "BorderColor",
          "DisabledBorderColor",
          "PressedBorderColor",
          "HoverBorderColor",
          "BorderStyle",
          "FocusedBorderColor",
          {
            "AFDDataSourceName": "",
            "AutoRuleBindingEnabled": false,
            "AutoRuleBindingString": "RGBA(255, 255, 255, 1)",
            "InvariantPropertyName": "Color",
            "IsLockable": false,
            "NameMapSourceSchema": "?"
          },
          "DisabledColor",
          "PressedColor",
          {
            "AFDDataSourceName": "",
            "AutoRuleBindingEnabled": false,
            "AutoRuleBindingString": "RGBA(255, 255, 255, 1)",
            "InvariantPropertyName": "HoverColor",
            "IsLockable": false,
            "NameMapSourceSchema": "?"
          },
          "DisplayMode",
          {
            "AFDDataSourceName": "",
            "AutoRuleBindingEnabled": false,
            "AutoRuleBindingString": "RGBA(56, 96, 178, 1)",
            "InvariantPropertyName": "Fill",
            "IsLockable": false,
            "NameMapSourceSchema": "?"
          },
          "DisabledFill",
          {
            "AFDDataSourceName": "",
            "AutoRuleBindingEnabled": false,
            "AutoRuleBindingString": "Self.Color",
            "InvariantPropertyName": "PressedFill",
            "IsLockable": false,
            "NameMapSourceSchema": "?"
          },
          {
            "AFDDataSourceName": "",
            "AutoRuleBindingEnabled": false,
            "AutoRuleBindingString": "ColorFade(RGBA(56, 96, 178, 1), -20%)",
            "InvariantPropertyName": "HoverFill",
            "IsLockable": false,
            "NameMapSourceSchema": "?"
          },
          "Font",
          {
            "AFDDataSourceName": "",
            "AutoRuleBindingEnabled": false,
            "AutoRuleBindingString": "",
            "InvariantPropertyName": "FontWeight",
            "IsLockable": false,
            "NameMapSourceSchema": "?"
          },
          {
            "AFDDataSourceName": "",
            "AutoRuleBindingEnabled": false,
            "AutoRuleBindingString": "",
            "InvariantPropertyName": "Align",
            "IsLockable": false,
            "NameMapSourceSchema": "?"
          },
          "VerticalAlign",
          "X",
          "Y",
          {
            "AFDDataSourceName": "",
            "AutoRuleBindingEnabled": false,
            "AutoRuleBindingString": "160",
            "InvariantPropertyName": "Width",
            "IsLockable": false,
            "NameMapSourceSchema": "?"
          },
          "Height",
          "ZIndex",
          {
            "AFDDataSourceName": "",
            "AutoRuleBindingEnabled": false,
            "AutoRuleBindingString": "",
            "InvariantPropertyName": "RadiusTopLeft",
            "IsLockable": false,
            "NameMapSourceSchema": "?"
          },
          {
            "AFDDataSourceName": "",
            "AutoRuleBindingEnabled": false,
            "AutoRuleBindingString": "",
            "InvariantPropertyName": "RadiusTopRight",
            "IsLockable": false,
            "NameMapSourceSchema": "?"
          },
          {
            "AFDDataSourceName": "",
            "AutoRuleBindingEnabled": false,
            "AutoRuleBindingString": "",
            "InvariantPropertyName": "RadiusBottomLeft",
            "IsLockable": false,
            "NameMapSourceSchema": "?"
          },
          {
            "AFDDataSourceName": "",
            "AutoRuleBindingEnabled": false,
            "AutoRuleBindingString": "",
            "InvariantPropertyName": "RadiusBottomRight",
            "IsLockable": false,
            "NameMapSourceSchema": "?"
          },
          {
            "AFDDataSourceName": "",
            "AutoRuleBindingEnabled": false,
            "AutoRuleBindingString": "",
            "InvariantPropertyName": "BorderThickness",
            "IsLockable": false,
            "NameMapSourceSchema": "?"
          },
          "FocusedBorderThickness",
          "Size",
          "Italic",
          "Underline",
          "Strikethrough",
          {
            "AFDDataSourceName": "",
            "AutoRuleBindingEnabled": false,
            "AutoRuleBindingString": "",
            "InvariantPropertyName": "PaddingLeft",
            "IsLockable": false,
            "NameMapSourceSchema": "?"
          },
          {
            "AFDDataSourceName": "",
            "AutoRuleBindingEnabled": false,
            "AutoRuleBindingString": "false",
            "InvariantPropertyName": "OnSelect",
            "IsLockable": false,
            "NameMapSourceSchema": "?"
          }
        ],
        "ControlUniqueId": "41",
        "HasDynamicProperties": false,
        "Index": 0,
        "IsAutoGenerated": false,
        "IsDataControl": false,
        "IsFromScreenLayout": false,
        "IsGroupControl": false,
        "IsLocked": false,
        "LayoutName": "",
        "MetaDataIDKey": "",
        "Name": "Button1_3",
        "Parent": "ModalConfirmation",
        "PersistMetaDataIDKey": false,
        "PublishOrderIndex": 1055,
        "Rules": [
          {
            "Category": "Data",
            "InvariantScript": "ModalConfirmation.RightBtnText",
            "Property": "Text",
            "RuleProviderType": "Unknown"
          },
          {
            "Category": "Design",
            "InvariantScript": "ColorFade(Self.Fill, -15%)",
            "Property": "BorderColor",
            "RuleProviderType": "Unknown"
          },
          {
            "Category": "Design",
            "InvariantScript": "RGBA(166, 166, 166, 1)",
            "Property": "DisabledBorderColor",
            "RuleProviderType": "Unknown"
          },
          {
            "Category": "Design",
            "InvariantScript": "Self.Fill",
            "Property": "PressedBorderColor",
            "RuleProviderType": "Unknown"
          },
          {
            "Category": "Design",
            "InvariantScript": "ColorFade(Self.BorderColor, 20%)",
            "Property": "HoverBorderColor",
            "RuleProviderType": "Unknown"
          },
          {
            "Category": "Design",
            "InvariantScript": "BorderStyle.Solid",
            "Property": "BorderStyle",
            "RuleProviderType": "Unknown"
          },
          {
            "Category": "Design",
            "InvariantScript": "Self.BorderColor",
            "Property": "FocusedBorderColor",
            "RuleProviderType": "Unknown"
          },
          {
            "Category": "Design",
            "InvariantScript": "RGBA(70, 70, 70, 1)",
            "Property": "Color",
            "RuleProviderType": "Unknown"
          },
          {
            "Category": "Design",
            "InvariantScript": "RGBA(166, 166, 166, 1)",
            "Property": "DisabledColor",
            "RuleProviderType": "Unknown"
          },
          {
            "Category": "Design",
            "InvariantScript": "Self.Fill",
            "Property": "PressedColor",
            "RuleProviderType": "Unknown"
          },
          {
            "Category": "Design",
            "InvariantScript": "RGBA(70, 70, 70, 1)",
            "Property": "HoverColor",
            "RuleProviderType": "Unknown"
          },
          {
            "Category": "Design",
            "InvariantScript": "DisplayMode.Edit",
            "Property": "DisplayMode",
            "RuleProviderType": "Unknown"
          },
          {
            "Category": "Design",
            "InvariantScript": "ModalConfirmation.RightBtnFill",
            "Property": "Fill",
            "RuleProviderType": "Unknown"
          },
          {
            "Category": "Design",
            "InvariantScript": "RGBA(244, 244, 244, 1)",
            "Property": "DisabledFill",
            "RuleProviderType": "Unknown"
          },
          {
            "Category": "Design",
            "InvariantScript": "ModalConfirmation.RightBtnFill",
            "Property": "PressedFill",
            "RuleProviderType": "Unknown"
          },
          {
            "Category": "Design",
            "InvariantScript": "ModalConfirmation.RightBtnFill",
            "Property": "HoverFill",
            "RuleProviderType": "Unknown"
          },
          {
            "Category": "Design",
            "InvariantScript": "Font.'Open Sans'",
            "Property": "Font",
            "RuleProviderType": "Unknown"
          },
          {
            "Category": "Design",
            "InvariantScript": "FontWeight.Normal",
            "Property": "FontWeight",
            "RuleProviderType": "Unknown"
          },
          {
            "Category": "Design",
            "InvariantScript": "Align.Left",
            "Property": "Align",
            "RuleProviderType": "Unknown"
          },
          {
            "Category": "Design",
            "InvariantScript": "VerticalAlign.Middle",
            "Property": "VerticalAlign",
            "RuleProviderType": "Unknown"
          },
          {
            "Category": "Design",
            "InvariantScript": "715",
            "Property": "X",
            "RuleProviderType": "Unknown"
          },
          {
            "Category": "Design",
            "InvariantScript": "440",
            "Property": "Y",
            "RuleProviderType": "Unknown"
          },
          {
            "Category": "Design",
            "InvariantScript": "165",
            "Property": "Width",
            "RuleProviderType": "Unknown"
          },
          {
            "Category": "Design",
            "InvariantScript": "40",
            "Property": "Height",
            "RuleProviderType": "Unknown"
          },
          {
            "Category": "Design",
            "InvariantScript": "6",
            "Property": "ZIndex",
            "RuleProviderType": "Unknown"
          },
          {
            "Category": "Design",
            "InvariantScript": "5",
            "Property": "RadiusTopLeft",
            "RuleProviderType": "Unknown"
          },
          {
            "Category": "Design",
            "InvariantScript": "5",
            "Property": "RadiusTopRight",
            "RuleProviderType": "Unknown"
          },
          {
            "Category": "Design",
            "InvariantScript": "5",
            "Property": "RadiusBottomLeft",
            "RuleProviderType": "Unknown"
          },
          {
            "Category": "Design",
            "InvariantScript": "5",
            "Property": "RadiusBottomRight",
            "RuleProviderType": "Unknown"
          },
          {
            "Category": "Design",
            "InvariantScript": "0",
            "Property": "BorderThickness",
            "RuleProviderType": "Unknown"
          },
          {
            "Category": "Design",
            "InvariantScript": "4",
            "Property": "FocusedBorderThickness",
            "RuleProviderType": "Unknown"
          },
          {
            "Category": "Design",
            "InvariantScript": "15",
            "Property": "Size",
            "RuleProviderType": "Unknown"
          },
          {
            "Category": "Design",
            "InvariantScript": "false",
            "Property": "Italic",
            "RuleProviderType": "Unknown"
          },
          {
            "Category": "Design",
            "InvariantScript": "false",
            "Property": "Underline",
            "RuleProviderType": "Unknown"
          },
          {
            "Category": "Design",
            "InvariantScript": "false",
            "Property": "Strikethrough",
            "RuleProviderType": "Unknown"
          },
          {
            "Category": "Design",
            "InvariantScript": "50",
            "Property": "PaddingLeft",
            "RuleProviderType": "Unknown"
          },
          {
            "Category": "Behavior",
            "InvariantScript": "",
            "Property": "OnSelect",
            "RuleProviderType": "Unknown"
          }
        ],
        "StyleName": "defaultButtonStyle",
        "Template": {
          "CustomGroupControlTemplateName": "",
          "FirstParty": true,
          "Id": "http://microsoft.com/appmagic/button",
          "IsComponentDefinition": false,
          "IsCustomGroupControlTemplate": false,
          "IsPremiumPcfControl": false,
          "LastModifiedTimestamp": "0",
          "Name": "button",
          "OverridableProperties": {},
          "Version": "2.2.0"
        },
        "Type": "ControlInfo",
        "VariantName": ""
      },
      {
        "AllowAccessToGlobals": true,
        "Children": [],
        "ControlPropertyState": [
          {
            "AFDDataSourceName": "",
            "AutoRuleBindingEnabled": false,
            "AutoRuleBindingString": "Icon.Printing3D",
            "InvariantPropertyName": "Icon",
            "IsLockable": false,
            "NameMapSourceSchema": "?"
          },
          {
            "AFDDataSourceName": "",
            "AutoRuleBindingEnabled": false,
            "AutoRuleBindingString": "RGBA(0, 18, 107, 1)",
            "InvariantPropertyName": "Color",
            "IsLockable": false,
            "NameMapSourceSchema": "?"
          },
          "DisabledColor",
          "PressedColor",
          "HoverColor",
          "Fill",
          "DisabledFill",
          "PressedFill",
          "HoverFill",
          "DisplayMode",
          "X",
          "Y",
          {
            "AFDDataSourceName": "",
            "AutoRuleBindingEnabled": false,
            "AutoRuleBindingString": "",
            "InvariantPropertyName": "Width",
            "IsLockable": false,
            "NameMapSourceSchema": "?"
          },
          {
            "AFDDataSourceName": "",
            "AutoRuleBindingEnabled": false,
            "AutoRuleBindingString": "",
            "InvariantPropertyName": "Height",
            "IsLockable": false,
            "NameMapSourceSchema": "?"
          },
          "BorderStyle",
          "BorderColor",
          "DisabledBorderColor",
          "PressedBorderColor",
          "HoverBorderColor",
          "FocusedBorderColor",
          "ZIndex",
          "BorderThickness",
          "FocusedBorderThickness"
        ],
        "ControlUniqueId": "42",
        "HasDynamicProperties": false,
        "Index": 0,
        "IsAutoGenerated": false,
        "IsDataControl": false,
        "IsFromScreenLayout": false,
        "IsGroupControl": false,
        "IsLocked": false,
        "LayoutName": "",
        "MetaDataIDKey": "",
        "Name": "Icon2_2",
        "Parent": "ModalConfirmation",
        "PersistMetaDataIDKey": false,
        "PublishOrderIndex": 1056,
        "Rules": [
          {
            "Category": "Design",
            "InvariantScript": "ModalConfirmation.LeftBtnIcon",
            "Property": "Icon",
            "RuleProviderType": "Unknown"
          },
          {
            "Category": "Design",
            "InvariantScript": "RGBA(255, 191, 0, 1)",
            "Property": "Color",
            "RuleProviderType": "Unknown"
          },
          {
            "Category": "Design",
            "InvariantScript": "RGBA(244, 244, 244, 1)",
            "Property": "DisabledColor",
            "RuleProviderType": "Unknown"
          },
          {
            "Category": "Design",
            "InvariantScript": "ColorFade(Self.Color, -20%)",
            "Property": "PressedColor",
            "RuleProviderType": "Unknown"
          },
          {
            "Category": "Design",
            "InvariantScript": "ColorFade(Self.Color, 20%)",
            "Property": "HoverColor",
            "RuleProviderType": "Unknown"
          },
          {
            "Category": "Design",
            "InvariantScript": "RGBA(0, 0, 0, 0)",
            "Property": "Fill",
            "RuleProviderType": "Unknown"
          },
          {
            "Category": "Design",
            "InvariantScript": "Self.Fill",
            "Property": "DisabledFill",
            "RuleProviderType": "Unknown"
          },
          {
            "Category": "Design",
            "InvariantScript": "Self.Fill",
            "Property": "PressedFill",
            "RuleProviderType": "Unknown"
          },
          {
            "Category": "Design",
            "InvariantScript": "Self.Fill",
            "Property": "HoverFill",
            "RuleProviderType": "Unknown"
          },
          {
            "Category": "Design",
            "InvariantScript": "DisplayMode.Edit",
            "Property": "DisplayMode",
            "RuleProviderType": "Unknown"
          },
          {
            "Category": "Design",
            "InvariantScript": "496",
            "Property": "X",
            "RuleProviderType": "Unknown"
          },
          {
            "Category": "Design",
            "InvariantScript": "445",
            "Property": "Y",
            "RuleProviderType": "Unknown"
          },
          {
            "Category": "Design",
            "InvariantScript": "30",
            "Property": "Width",
            "RuleProviderType": "Unknown"
          },
          {
            "Category": "Design",
            "InvariantScript": "30",
            "Property": "Height",
            "RuleProviderType": "Unknown"
          },
          {
            "Category": "Design",
            "InvariantScript": "BorderStyle.Solid",
            "Property": "BorderStyle",
            "RuleProviderType": "Unknown"
          },
          {
            "Category": "Design",
            "InvariantScript": "RGBA(0, 18, 107, 1)",
            "Property": "BorderColor",
            "RuleProviderType": "Unknown"
          },
          {
            "Category": "Design",
            "InvariantScript": "RGBA(166, 166, 166, 1)",
            "Property": "DisabledBorderColor",
            "RuleProviderType": "Unknown"
          },
          {
            "Category": "Design",
            "InvariantScript": "ColorFade(Self.BorderColor, -20%)",
            "Property": "PressedBorderColor",
            "RuleProviderType": "Unknown"
          },
          {
            "Category": "Design",
            "InvariantScript": "ColorFade(Self.BorderColor, 20%)",
            "Property": "HoverBorderColor",
            "RuleProviderType": "Unknown"
          },
          {
            "Category": "Design",
            "InvariantScript": "Self.BorderColor",
            "Property": "FocusedBorderColor",
            "RuleProviderType": "Unknown"
          },
          {
            "Category": "Design",
            "InvariantScript": "5",
            "Property": "ZIndex",
            "RuleProviderType": "Unknown"
          },
          {
            "Category": "Design",
            "InvariantScript": "0",
            "Property": "BorderThickness",
            "RuleProviderType": "Unknown"
          },
          {
            "Category": "Design",
            "InvariantScript": "2",
            "Property": "FocusedBorderThickness",
            "RuleProviderType": "Unknown"
          }
        ],
        "StyleName": "defaultIconStyle",
        "Template": {
          "CustomGroupControlTemplateName": "",
          "FirstParty": true,
          "Id": "http://microsoft.com/appmagic/icon",
          "IsComponentDefinition": false,
          "IsCustomGroupControlTemplate": false,
          "IsPremiumPcfControl": false,
          "LastModifiedTimestamp": "0",
          "Name": "icon",
          "OverridableProperties": {},
          "Version": "2.5.0"
        },
        "Type": "ControlInfo",
        "VariantName": "3DPrinting"
      },
      {
        "AllowAccessToGlobals": true,
        "Children": [],
        "ControlPropertyState": [
          {
            "AFDDataSourceName": "",
            "AutoRuleBindingEnabled": false,
            "AutoRuleBindingString": "Icon.Printing3D",
            "InvariantPropertyName": "Icon",
            "IsLockable": false,
            "NameMapSourceSchema": "?"
          },
          {
            "AFDDataSourceName": "",
            "AutoRuleBindingEnabled": false,
            "AutoRuleBindingString": "RGBA(0, 18, 107, 1)",
            "InvariantPropertyName": "Color",
            "IsLockable": false,
            "NameMapSourceSchema": "?"
          },
          "DisabledColor",
          "PressedColor",
          "HoverColor",
          "Fill",
          "DisabledFill",
          "PressedFill",
          "HoverFill",
          "DisplayMode",
          "X",
          "Y",
          {
            "AFDDataSourceName": "",
            "AutoRuleBindingEnabled": false,
            "AutoRuleBindingString": "",
            "InvariantPropertyName": "Width",
            "IsLockable": false,
            "NameMapSourceSchema": "?"
          },
          {
            "AFDDataSourceName": "",
            "AutoRuleBindingEnabled": false,
            "AutoRuleBindingString": "",
            "InvariantPropertyName": "Height",
            "IsLockable": false,
            "NameMapSourceSchema": "?"
          },
          "BorderStyle",
          "BorderColor",
          "DisabledBorderColor",
          "PressedBorderColor",
          "HoverBorderColor",
          "FocusedBorderColor",
          "ZIndex",
          "BorderThickness",
          "FocusedBorderThickness"
        ],
        "ControlUniqueId": "43",
        "HasDynamicProperties": false,
        "Index": 0,
        "IsAutoGenerated": false,
        "IsDataControl": false,
        "IsFromScreenLayout": false,
        "IsGroupControl": false,
        "IsLocked": false,
        "LayoutName": "",
        "MetaDataIDKey": "",
        "Name": "Icon2_3",
        "Parent": "ModalConfirmation",
        "PersistMetaDataIDKey": false,
        "PublishOrderIndex": 1057,
        "Rules": [
          {
            "Category": "Design",
            "InvariantScript": "ModalConfirmation.RightBtnIcon",
            "Property": "Icon",
            "RuleProviderType": "Unknown"
          },
          {
            "Category": "Design",
            "InvariantScript": "RGBA(255, 191, 0, 1)",
            "Property": "Color",
            "RuleProviderType": "Unknown"
          },
          {
            "Category": "Design",
            "InvariantScript": "RGBA(244, 244, 244, 1)",
            "Property": "DisabledColor",
            "RuleProviderType": "Unknown"
          },
          {
            "Category": "Design",
            "InvariantScript": "ColorFade(Self.Color, -20%)",
            "Property": "PressedColor",
            "RuleProviderType": "Unknown"
          },
          {
            "Category": "Design",
            "InvariantScript": "ColorFade(Self.Color, 20%)",
            "Property": "HoverColor",
            "RuleProviderType": "Unknown"
          },
          {
            "Category": "Design",
            "InvariantScript": "RGBA(0, 0, 0, 0)",
            "Property": "Fill",
            "RuleProviderType": "Unknown"
          },
          {
            "Category": "Design",
            "InvariantScript": "Self.Fill",
            "Property": "DisabledFill",
            "RuleProviderType": "Unknown"
          },
          {
            "Category": "Design",
            "InvariantScript": "Self.Fill",
            "Property": "PressedFill",
            "RuleProviderType": "Unknown"
          },
          {
            "Category": "Design",
            "InvariantScript": "Self.Fill",
            "Property": "HoverFill",
            "RuleProviderType": "Unknown"
          },
          {
            "Category": "Design",
            "InvariantScript": "DisplayMode.Edit",
            "Property": "DisplayMode",
            "RuleProviderType": "Unknown"
          },
          {
            "Category": "Design",
            "InvariantScript": "725",
            "Property": "X",
            "RuleProviderType": "Unknown"
          },
          {
            "Category": "Design",
            "InvariantScript": "445",
            "Property": "Y",
            "RuleProviderType": "Unknown"
          },
          {
            "Category": "Design",
            "InvariantScript": "30",
            "Property": "Width",
            "RuleProviderType": "Unknown"
          },
          {
            "Category": "Design",
            "InvariantScript": "30",
            "Property": "Height",
            "RuleProviderType": "Unknown"
          },
          {
            "Category": "Design",
            "InvariantScript": "BorderStyle.Solid",
            "Property": "BorderStyle",
            "RuleProviderType": "Unknown"
          },
          {
            "Category": "Design",
            "InvariantScript": "RGBA(0, 18, 107, 1)",
            "Property": "BorderColor",
            "RuleProviderType": "Unknown"
          },
          {
            "Category": "Design",
            "InvariantScript": "RGBA(166, 166, 166, 1)",
            "Property": "DisabledBorderColor",
            "RuleProviderType": "Unknown"
          },
          {
            "Category": "Design",
            "InvariantScript": "ColorFade(Self.BorderColor, -20%)",
            "Property": "PressedBorderColor",
            "RuleProviderType": "Unknown"
          },
          {
            "Category": "Design",
            "InvariantScript": "ColorFade(Self.BorderColor, 20%)",
            "Property": "HoverBorderColor",
            "RuleProviderType": "Unknown"
          },
          {
            "Category": "Design",
            "InvariantScript": "Self.BorderColor",
            "Property": "FocusedBorderColor",
            "RuleProviderType": "Unknown"
          },
          {
            "Category": "Design",
            "InvariantScript": "7",
            "Property": "ZIndex",
            "RuleProviderType": "Unknown"
          },
          {
            "Category": "Design",
            "InvariantScript": "0",
            "Property": "BorderThickness",
            "RuleProviderType": "Unknown"
          },
          {
            "Category": "Design",
            "InvariantScript": "2",
            "Property": "FocusedBorderThickness",
            "RuleProviderType": "Unknown"
          }
        ],
        "StyleName": "defaultIconStyle",
        "Template": {
          "CustomGroupControlTemplateName": "",
          "FirstParty": true,
          "Id": "http://microsoft.com/appmagic/icon",
          "IsComponentDefinition": false,
          "IsCustomGroupControlTemplate": false,
          "IsPremiumPcfControl": false,
          "LastModifiedTimestamp": "0",
          "Name": "icon",
          "OverridableProperties": {},
          "Version": "2.5.0"
        },
        "Type": "ControlInfo",
        "VariantName": "3DPrinting"
      }
    ],
    "ControlPropertyState": [
      {
        "AFDDataSourceName": "",
        "AutoRuleBindingEnabled": false,
        "AutoRuleBindingString": "RGBA(0, 0, 0, 0)",
        "InvariantPropertyName": "Fill",
        "IsLockable": false,
        "NameMapSourceSchema": "?"
      },
      {
        "AFDDataSourceName": "",
        "AutoRuleBindingEnabled": false,
        "AutoRuleBindingString": "640",
        "InvariantPropertyName": "Height",
        "IsLockable": false,
        "NameMapSourceSchema": "?"
      },
      {
        "AFDDataSourceName": "",
        "AutoRuleBindingEnabled": false,
        "AutoRuleBindingString": "640",
        "InvariantPropertyName": "Width",
        "IsLockable": false,
        "NameMapSourceSchema": "?"
      },
      "X",
      "Y",
      "ZIndex",
      {
        "AFDDataSourceName": "",
        "AutoRuleBindingEnabled": false,
        "AutoRuleBindingString": "\"Text\"",
        "InvariantPropertyName": "ModalIcon",
        "IsLockable": false,
        "NameMapSourceSchema": "?"
      },
      {
        "AFDDataSourceName": "",
        "AutoRuleBindingEnabled": false,
        "AutoRuleBindingString": "RGBA(0, 0, 0, 1)",
        "InvariantPropertyName": "ModalIconColor",
        "IsLockable": false,
        "NameMapSourceSchema": "?"
      },
      {
        "AFDDataSourceName": "",
        "AutoRuleBindingEnabled": false,
        "AutoRuleBindingString": "\"Text\"",
        "InvariantPropertyName": "ModalText",
        "IsLockable": false,
        "NameMapSourceSchema": "?"
      },
      {
        "AFDDataSourceName": "",
        "AutoRuleBindingEnabled": false,
        "AutoRuleBindingString": "\"Text\"",
        "InvariantPropertyName": "LeftBtnText",
        "IsLockable": false,
        "NameMapSourceSchema": "?"
      },
      {
        "AFDDataSourceName": "",
        "AutoRuleBindingEnabled": false,
        "AutoRuleBindingString": "\"Text\"",
        "InvariantPropertyName": "LeftBtnIcon",
        "IsLockable": false,
        "NameMapSourceSchema": "?"
      },
      {
        "AFDDataSourceName": "",
        "AutoRuleBindingEnabled": false,
        "AutoRuleBindingString": "\"Text\"",
        "InvariantPropertyName": "RightBtnIcon",
        "IsLockable": false,
        "NameMapSourceSchema": "?"
      },
      {
        "AFDDataSourceName": "",
        "AutoRuleBindingEnabled": false,
        "AutoRuleBindingString": "\"Text\"",
        "InvariantPropertyName": "RightBtnText",
        "IsLockable": false,
        "NameMapSourceSchema": "?"
      },
      {
        "AFDDataSourceName": "",
        "AutoRuleBindingEnabled": false,
        "AutoRuleBindingString": "RGBA(0, 0, 0, 1)",
        "InvariantPropertyName": "RightBtnFill",
        "IsLockable": false,
        "NameMapSourceSchema": "?"
      }
    ],
    "LastModifiedTimestamp": "638230496898234188",
    "Name": "ModalConfirmation",
    "Rules": [
      {
        "Category": "Data",
        "InvariantScript": "Icon.Error",
        "Property": "ModalIcon",
        "RuleProviderType": "System"
      },
      {
        "Category": "Data",
        "InvariantScript": "Color.Red",
        "Property": "ModalIconColor",
        "RuleProviderType": "System"
      },
      {
        "Category": "Data",
        "InvariantScript": "\"Deseja eliminar o registo?\"",
        "Property": "ModalText",
        "RuleProviderType": "System"
      },
      {
        "Category": "Data",
        "InvariantScript": "\"Confirmar\"",
        "Property": "LeftBtnText",
        "RuleProviderType": "System"
      },
      {
        "Category": "Data",
        "InvariantScript": "Icon.Check",
        "Property": "LeftBtnIcon",
        "RuleProviderType": "System"
      },
      {
        "Category": "Data",
        "InvariantScript": "Icon.Cancel",
        "Property": "RightBtnIcon",
        "RuleProviderType": "System"
      },
      {
        "Category": "Data",
        "InvariantScript": "\"CANCELAR\"",
        "Property": "RightBtnText",
        "RuleProviderType": "System"
      },
      {
        "Category": "Data",
        "InvariantScript": "ColorFade(Color.Red, 0.9)",
        "Property": "RightBtnFill",
        "RuleProviderType": "System"
      },
      {
        "Category": "Design",
        "InvariantScript": "RGBA(77, 77, 77, 0.3)",
        "Property": "Fill",
        "RuleProviderType": "System"
      },
      {
        "Category": "Design",
        "InvariantScript": "App.Height",
        "Property": "Height",
        "RuleProviderType": "System"
      },
      {
        "Category": "Design",
        "InvariantScript": "App.Width",
        "Property": "Width",
        "RuleProviderType": "System"
      },
      {
        "Category": "Design",
        "InvariantScript": "0",
        "Property": "X",
        "RuleProviderType": "Unknown"
      },
      {
        "Category": "Design",
        "InvariantScript": "0",
        "Property": "Y",
        "RuleProviderType": "Unknown"
      },
      {
        "Category": "Design",
        "InvariantScript": "1",
        "Property": "ZIndex",
        "RuleProviderType": "Unknown"
      }
    ]
  },
  "ComponentManifest": {
    "AllowAccessToGlobals": false,
    "AllowCustomization": true,
    "Description": "",
    "Name": "ModalConfirmation",
    "TemplateGuid": "eb24e4724ed04a619ab834c43dfccdf3"
  },
  "ComponentType": "CanvasComponent",
  "CustomGroupControlTemplateName": "",
  "CustomProperties": [
    {
      "Category": 0,
      "DisplayName": "Modal Icon",
      "Hidden": false,
      "Name": "ModalIcon",
      "PropertyDataTypeKey": "String",
      "Tooltip": "A custom property",
      "Type": "{\"Version\":\"1.332\",\"Type\":{\"Name\":\"Root\",\"Kind\":\"String\",\"EnumString\":\"\",\"Type\":[]}}"
    },
    {
      "Category": 0,
      "DisplayName": "Modal Icon Color",
      "Hidden": false,
      "Name": "ModalIconColor",
      "PropertyDataTypeKey": "Color",
      "Tooltip": "A custom property",
      "Type": "{\"Version\":\"1.332\",\"Type\":{\"Name\":\"Root\",\"Kind\":\"Color\",\"EnumString\":\"\",\"Type\":[]}}"
    },
    {
      "Category": 0,
      "DisplayName": "Modal Text",
      "Hidden": false,
      "Name": "ModalText",
      "PropertyDataTypeKey": "String",
      "Tooltip": "A custom property",
      "Type": "{\"Version\":\"1.332\",\"Type\":{\"Name\":\"Root\",\"Kind\":\"String\",\"EnumString\":\"\",\"Type\":[]}}"
    },
    {
      "Category": 0,
      "DisplayName": "Left Btn Text",
      "Hidden": false,
      "Name": "LeftBtnText",
      "PropertyDataTypeKey": "String",
      "Tooltip": "A custom property",
      "Type": "{\"Version\":\"1.332\",\"Type\":{\"Name\":\"Root\",\"Kind\":\"String\",\"EnumString\":\"\",\"Type\":[]}}"
    },
    {
      "Category": 0,
      "DisplayName": "Left Btn Icon",
      "Hidden": false,
      "Name": "LeftBtnIcon",
      "PropertyDataTypeKey": "String",
      "Tooltip": "A custom property",
      "Type": "{\"Version\":\"1.332\",\"Type\":{\"Name\":\"Root\",\"Kind\":\"String\",\"EnumString\":\"\",\"Type\":[]}}"
    },
    {
      "Category": 0,
      "DisplayName": "Right Btn Icon",
      "Hidden": false,
      "Name": "RightBtnIcon",
      "PropertyDataTypeKey": "String",
      "Tooltip": "A custom property",
      "Type": "{\"Version\":\"1.332\",\"Type\":{\"Name\":\"Root\",\"Kind\":\"String\",\"EnumString\":\"\",\"Type\":[]}}"
    },
    {
      "Category": 0,
      "DisplayName": "Right Btn Text",
      "Hidden": false,
      "Name": "RightBtnText",
      "PropertyDataTypeKey": "String",
      "Tooltip": "A custom property",
      "Type": "{\"Version\":\"1.332\",\"Type\":{\"Name\":\"Root\",\"Kind\":\"String\",\"EnumString\":\"\",\"Type\":[]}}"
    },
    {
      "Category": 0,
      "DisplayName": "Right Btn Fill",
      "Hidden": false,
      "Name": "RightBtnFill",
      "PropertyDataTypeKey": "Color",
      "Tooltip": "A custom property",
      "Type": "{\"Version\":\"1.332\",\"Type\":{\"Name\":\"Root\",\"Kind\":\"Color\",\"EnumString\":\"\",\"Type\":[]}}"
    }
  ],
  "FirstParty": true,
  "Id": "http://microsoft.com/appmagic/Component",
  "IsComponentLocked": false,
  "IsComponentTemplate": true,
  "IsCustomGroupControlTemplate": false,
  "IsPcfControl": false,
  "IsPremiumPcfControl": false,
  "IsWidgetTemplate": false,
  "LastModifiedTimestamp": "638230496898234188",
  "Name": "eb24e4724ed04a619ab834c43dfccdf3",
  "OverridableProperties": {},
  "Version": "638193246716139455"
}